README.txt
setup.py
python/bioinf_utilities.egg-info/PKG-INFO
python/bioinf_utilities.egg-info/SOURCES.txt
python/bioinf_utilities.egg-info/dependency_links.txt
python/bioinf_utilities.egg-info/requires.txt
python/bioinf_utilities.egg-info/top_level.txt
python/bioinfutils/__init__.py
python/corebio/LICENSE.txt
python/corebio/__init__.py
python/corebio/_version.py
python/corebio/data.py
python/corebio/moremath.py
python/corebio/seq.py
python/corebio/transform.py
scripts/bed-add-names
scripts/bed-get-regions
scripts/bed-info
scripts/bedtools2fasta
scripts/bgr2bed
scripts/make-GREAT-bg
scripts/seq-filter-empty
scripts/seq-filter-short
scripts/seq-head
scripts/seq-info
scripts/seq-mask-lower
scripts/seq-match-lengths
scripts/seq-shorten
scripts/seq-shuffle
scripts/seq-strip-Ns
scripts/seq-subtract
scripts/seq-tally
scripts/seq-upper
scripts/subsample