Metadata-Version: 1.0
Name: bioinf-utilities
Version: 1.3.24
Summary: Some utilities for sequence analysis
Home-page: http://sysbio.mrc-bsu.cam.ac.uk/group/index.php/John_Reid
Author: John Reid
Author-email: johnbaronreid@netscape.net
License: UNKNOWN
Platform: UNKNOWN
